[{"cause":"Breast Cancer","htmlcolor":"pink"},{"cause":"Birth Parents","htmlcolor":"pink"},{"cause":"Nursing Mothers","htmlcolor":"pink"},{"cause":"Duchenne Muscular Dystrophy","htmlcolor":"limegreen"},{"cause":"Gastroschisis","htmlcolor":"limegreen"},{"cause":"Lyme Disease","htmlcolor":"limegreen"},{"cause":"Lymphoma","htmlcolor":"limegreen"},{"cause":"Muscular Dystrophy","htmlcolor":"limegreen"},{"cause":"Non-Hodgkin&#39;s Lymphoma","htmlcolor":"limegreen"},{"cause":"Sandhoff Disease","htmlcolor":"limegreen"},{"cause":"Uterine Cancer","htmlcolor":"peachpuff"},{"cause":"Endometrial Cancer","htmlcolor":"peachpuff"},{"cause":"AIDS/HIV","htmlcolor":"red"},{"cause":"Aperts Syndrome","htmlcolor":"red"},{"cause":"Bronchiolitis Obliterans (BOS)","htmlcolor":"red"},{"cause":"Burn Victims","htmlcolor":"red"},{"cause":"Cardiovascular Disease","htmlcolor":"red"},{"cause":"Congenital Heart Disease","htmlcolor":"red"},{"cause":"Congestive Heart Failure","htmlcolor":"red"},{"cause":"Courage and Inspiration","htmlcolor":"red"},{"cause":"DARE","htmlcolor":"red"},{"cause":"Driving under the Influence","htmlcolor":"red"},{"cause":"Epidermolysis Bellosa","htmlcolor":"red"},{"cause":"Factor XI Deficiency","htmlcolor":"red"},{"cause":"Heart Disease","htmlcolor":"red"},{"cause":"Hemophilia","htmlcolor":"red"},{"cause":"High Blood Pressure","htmlcolor":"red"},{"cause":"Huffing","htmlcolor":"red"},{"cause":"Hypertension","htmlcolor":"red"},{"cause":"Inhalant Abuse","htmlcolor":"red"},{"cause":"Long Q-T Syndrome","htmlcolor":"red"},{"cause":"Wolf-Parkinson-White","htmlcolor":"red"},{"cause":"MADD","htmlcolor":"red"},{"cause":"Marfan Syndrome","htmlcolor":"red"},{"cause":"Project Red Flag","htmlcolor":"red"},{"cause":"Reflex Sympathetic Dystrophy","htmlcolor":"red"},{"cause":"Sniffing Abuse","htmlcolor":"red"},{"cause":"Stroke","htmlcolor":"red"},{"cause":"Substance Abuse","htmlcolor":"red"},{"cause":"Thrombotic Thrombocytopenic Purpura","htmlcolor":"red"},{"cause":"Von Willebrand&#39;s Disease","htmlcolor":"red"},{"cause":"Wegener&#39;s Granulomatosis","htmlcolor":"red"},{"cause":"Congenital Heart Defects","htmlcolor":"red"},{"cause":"Diamond Blackfan Anemia","htmlcolor":"red"},{"cause":"Evans Syndrome","htmlcolor":"red"},{"cause":"Lymphoma","htmlcolor":"red"},{"cause":"Supraventricular Tachycardia","htmlcolor":"red"},{"cause":"Tuberculosis","htmlcolor":"red"},{"cause":"Agoraphobia","htmlcolor":"teal"},{"cause":"Anxiety Disorder","htmlcolor":"teal"},{"cause":"Batten Disease","htmlcolor":"teal"},{"cause":"Cervical Cancer","htmlcolor":"teal"},{"cause":"Chari Malformation","htmlcolor":"teal"},{"cause":"Ectodermal Dysphasia","htmlcolor":"teal"},{"cause":"Food Allergies","htmlcolor":"teal"},{"cause":"Fragile X Syndrome","htmlcolor":"teal"},{"cause":"Marker X Syndrome","htmlcolor":"teal"},{"cause":"Martin-Bell Syndrome","htmlcolor":"teal"},{"cause":"Myasthenia Gravis","htmlcolor":"teal"},{"cause":"Ovarian Cancer","htmlcolor":"teal"},{"cause":"Panic Disorder","htmlcolor":"teal"},{"cause":"Polycystic Kidney Disease (PKD)","htmlcolor":"teal"},{"cause":"Polycycstic Ovarian Syndrome","htmlcolor":"teal"},{"cause":"Post Traumatic Stress Disorder (PTSD)","htmlcolor":"teal"},{"cause":"Progressive Supanuclear Palsy","htmlcolor":"teal"},{"cause":"Rape","htmlcolor":"teal"},{"cause":"Sexual Assault","htmlcolor":"teal"},{"cause":"Substance Abuse","htmlcolor":"teal"},{"cause":"Trigeminal Neuralgia (TN)","htmlcolor":"teal"},{"cause":"Tsunami Victims","htmlcolor":"teal"},{"cause":"Dissociative Identity Disorder","htmlcolor":"teal"},{"cause":"Obsessive-Compulsive Disorder","htmlcolor":"teal"},{"cause":"Uterine Cancer","htmlcolor":"teal"},{"cause":"BiPolar Disorder","htmlcolor":"green"},{"cause":"Bronchiolitis Obliterans (BOS)","htmlcolor":"green"},{"cause":"Cerebral Palsy","htmlcolor":"green"},{"cause":"Childhood Depression","htmlcolor":"green"},{"cause":"Depression","htmlcolor":"green"},{"cause":"The Environment","htmlcolor":"green"},{"cause":"Eye Injury Prevention","htmlcolor":"green"},{"cause":"Worker Safety","htmlcolor":"yellow"},{"cause":"Freedom","htmlcolor":"green"},{"cause":"Glaucoma","htmlcolor":"green"},{"cause":"Growth & rebuilding","htmlcolor":"green"},{"cause":"Kidney Cancer & disease","htmlcolor":"green"},{"cause":"Kidney Donation","htmlcolor":"green"},{"cause":"Leukemia","htmlcolor":"green"},{"cause":"Literacy","htmlcolor":"green"},{"cause":"Living Organ Donation","htmlcolor":"green"},{"cause":"Manic Depression","htmlcolor":"green"},{"cause":"Mental Health","htmlcolor":"green"},{"cause":"Mental Retardation","htmlcolor":"green"},{"cause":"Missing Children","htmlcolor":"green"},{"cause":"Nephrotic Syndrome","htmlcolor":"green"},{"cause":"Neural Tube Defects","htmlcolor":"green"},{"cause":"Organ Donation","htmlcolor":"green"},{"cause":"Organ Transplant","htmlcolor":"green"},{"cause":"Primary Sclerosing Cholangitis","htmlcolor":"green"},{"cause":"Safe Driving","htmlcolor":"green"},{"cause":"Pedestrian Safety","htmlcolor":"green"},{"cause":"Save Darfur","htmlcolor":"green"},{"cause":"Spinal Cord Injury and research","htmlcolor":"green"},{"cause":"Stem Cell donor and Research","htmlcolor":"green"},{"cause":"Tissue Donation","htmlcolor":"green"},{"cause":"Tourette&#39;s Syndrome","htmlcolor":"green"},{"cause":"Traumatic Brain Injury","htmlcolor":"green"},{"cause":"Von Hippel Lindau Syndrome","htmlcolor":"green"},{"cause":"Bone Marrow Donation","htmlcolor":"green"},{"cause":"Fibrodysplasia Ossifican&#39;s Progressiva","htmlcolor":"green"},{"cause":"Mitochondrial Disease","htmlcolor":"green"},{"cause":"Neurofibromatosis","htmlcolor":"green"},{"cause":"Allergies","htmlcolor":"gray"},{"cause":"Alpha-1 Antitrypsin Deficiency","htmlcolor":"gray"},{"cause":"Aphasia","htmlcolor":"gray"},{"cause":"Asthma","htmlcolor":"gray"},{"cause":"Brain Cancer","htmlcolor":"gray"},{"cause":"Brain Tumors","htmlcolor":"gray"},{"cause":"Diabetes","htmlcolor":"gray"},{"cause":"Borderline Personality Disorder","htmlcolor":"gray"},{"cause":"Amniotic Fluid Embolism","htmlcolor":"pink,blue"},{"cause":"Baby Safe Haven","htmlcolor":"pink,blue"},{"cause":"Birth defects","htmlcolor":"pink,blue"},{"cause":"Male Breast Cancer","htmlcolor":"pink,blue"},{"cause":"Hyperemesis Graviduram","htmlcolor":"pink,blue"},{"cause":"Hyperammonemia","htmlcolor":"pink,blue"},{"cause":"Infant Loss","htmlcolor":"pink,blue"},{"cause":"Infertility","htmlcolor":"pink,blue"},{"cause":"Miscarriage","htmlcolor":"pink,blue"},{"cause":"Pregnancy Loss","htmlcolor":"pink,blue"},{"cause":"Premature Birth","htmlcolor":"pink,blue"},{"cause":"Stillbirth","htmlcolor":"pink,blue"},{"cause":"Sudden Infant Death Syndrome (SIDS)","htmlcolor":"pink,blue"},{"cause":"Turners Syndrome","htmlcolor":"pink,blue"},{"cause":"chILD (Pediatric bronchiolitis obliterans).","htmlcolor":"pink,blue"},{"cause":"Twin to Twin transfusion syndrome","htmlcolor":"pink,blue"},{"cause":"Hodgkin&#39;s Disease","htmlcolor":"violet"},{"cause":"Testicular Cancer","htmlcolor":"violet"},{"cause":"Agent Orange","htmlcolor":"orange"},{"cause":"Cultural Diversity","htmlcolor":"orange"},{"cause":"Hunger","htmlcolor":"orange"},{"cause":"Leukemia","htmlcolor":"orange"},{"cause":"Lupus","htmlcolor":"orange"},{"cause":"Melanoma","htmlcolor":"orange"},{"cause":"Kidney Cancer (Renal Cell Carcinoma)","htmlcolor":"orange"},{"cause":"Motorcycle Safety","htmlcolor":"orange"},{"cause":"Multiple sclerosis (MS)","htmlcolor":"orange"},{"cause":"Reflex Sympathetic Dystrophy Syndrome","htmlcolor":"orange"},{"cause":"Self Injury","htmlcolor":"orange"},{"cause":"Racial Tolerance","htmlcolor":"orange"},{"cause":"Prader-Willi Syndrome","htmlcolor":"orange"},{"cause":"Adoptee","htmlcolor":"white"},{"cause":"Adoption","htmlcolor":"white"},{"cause":"Anti-Pornography","htmlcolor":"white"},{"cause":"Anti-War","htmlcolor":"white"},{"cause":"Blindness","htmlcolor":"white"},{"cause":"Bone Cancer","htmlcolor":"white"},{"cause":"Child exploitation","htmlcolor":"white"},{"cause":"Child Sexual Abuse/Assault","htmlcolor":"white"},{"cause":"Community Support","htmlcolor":"white"},{"cause":"Congenital Cataracts","htmlcolor":"white"},{"cause":"Elderly Affairs","htmlcolor":"white"},{"cause":"Hernia","htmlcolor":"white"},{"cause":"Holocaust Remembrance","htmlcolor":"white"},{"cause":"Innocence","htmlcolor":"white"},{"cause":"Multiple Hereditary Exostoses","htmlcolor":"white"},{"cause":"Molestation Survivor","htmlcolor":"white"},{"cause":"On-line Sexual Predator Awareness & Internet Safety","htmlcolor":"white"},{"cause":"Peace","htmlcolor":"white"},{"cause":"Postpartum Depression","htmlcolor":"white"},{"cause":"Retinoblastoma","htmlcolor":"white"},{"cause":"Right to Life","htmlcolor":"white"},{"cause":"Safe Motherhood","htmlcolor":"white"},{"cause":"Salvation Army","htmlcolor":"white"},{"cause":"Scoliosis","htmlcolor":"white"},{"cause":"Stalking","htmlcolor":"white"},{"cause":"Student Sexual Abuse","htmlcolor":"white"},{"cause":"Teen Pregnancy Prevention","htmlcolor":"white"},{"cause":"Anti-Child Pornography","htmlcolor":"white"},{"cause":"Bone Disease","htmlcolor":"white"},{"cause":"Osteoporosis","htmlcolor":"white"},{"cause":"Victims of Terrorism","htmlcolor":"white"},{"cause":"Hope & Support","htmlcolor":"white"},{"cause":"Alveolar Rhabdomyosarcoma","htmlcolor":"gold"},{"cause":"Childhood Cancer","htmlcolor":"gold"},{"cause":"COPD","htmlcolor":"gold"},{"cause":"Embryonal Rhabdomyosarcoma","htmlcolor":"gold"},{"cause":"undefined","htmlcolor":"gold"},{"cause":"Osteosarcoma","htmlcolor":"gold"},{"cause":"Accidents","htmlcolor":"black"},{"cause":"Amish Support","htmlcolor":"black"},{"cause":"Anti-Terrorism","htmlcolor":"black"},{"cause":"Gang Prevention","htmlcolor":"black"},{"cause":"Gun Control","htmlcolor":"black"},{"cause":"Melanoma","htmlcolor":"black"},{"cause":"Narcolepsy","htmlcolor":"black"},{"cause":"POW/MIA","htmlcolor":"black"},{"cause":"Primary Biliary Cirrhosis","htmlcolor":"black"},{"cause":"Sleep Apnea","htmlcolor":"black"},{"cause":"Sleep Disorders","htmlcolor":"black"},{"cause":"Students for Gun Control and Trauma","htmlcolor":"black"},{"cause":"Mourning","htmlcolor":"black"},{"cause":"Anti-Tobacco","htmlcolor":"brown"},{"cause":"Colon Cancer","htmlcolor":"brown"},{"cause":"Colorectal Cancer","htmlcolor":"brown"},{"cause":"Familia Polyposis","htmlcolor":"brown"},{"cause":"Tobacco Awareness","htmlcolor":"brown"},{"cause":"Adhesions","htmlcolor":"darkred"},{"cause":"AV Malformation","htmlcolor":"darkred"},{"cause":"Brain Aneurysm","htmlcolor":"darkred"},{"cause":"Cesarean Section","htmlcolor":"darkred"},{"cause":"Cystic Hygroma","htmlcolor":"darkred"},{"cause":"Disabled Adults","htmlcolor":"darkred"},{"cause":"Factor V Leiden","htmlcolor":"darkred"},{"cause":"Headaches","htmlcolor":"darkred"},{"cause":"Hereditary Hemochromatosis","htmlcolor":"darkred"},{"cause":"Hospice Care","htmlcolor":"darkred"},{"cause":"Lymphatic Malformation","htmlcolor":"darkred"},{"cause":"Meningitis","htmlcolor":"darkred"},{"cause":"Meningococcal Meningitis","htmlcolor":"darkred"},{"cause":"PHACES","htmlcolor":"darkred"},{"cause":"Post-Polio Syndrome","htmlcolor":"darkred"},{"cause":"Sickle Cell Anemia","htmlcolor":"darkred"},{"cause":"Sturge-Weber Syndrome","htmlcolor":"darkred"},{"cause":"Thrombophilia","htmlcolor":"darkred"},{"cause":"Williams Syndrome","htmlcolor":"darkred"},{"cause":"Antiphospholipid Antibody Syndrome","htmlcolor":"darkred"},{"cause":"Hemangioma","htmlcolor":"darkred"},{"cause":"Vascular Malformation","htmlcolor":"darkred"},{"cause":"Hughes Syndrome","htmlcolor":"darkred"},{"cause":"Multiple Myeloma","htmlcolor":"darkred"},{"cause":"Attention deficit disorder (ADD)","htmlcolor":"purple"},{"cause":"Attention deficit hyperactivity disorder (ADHD)","htmlcolor":"purple"},{"cause":"Animal Abuse","htmlcolor":"purple"},{"cause":"Anit-Violence","htmlcolor":"purple"},{"cause":"Arnold Chiari Malformation","htmlcolor":"purple"},{"cause":"Chronic Pain","htmlcolor":"purple"},{"cause":"Colitis","htmlcolor":"purple"},{"cause":"Crohn&#39;s Disease","htmlcolor":"purple"},{"cause":"Cystic Fibrosis","htmlcolor":"purple"},{"cause":"Domestic Violence","htmlcolor":"purple"},{"cause":"Epilepsy","htmlcolor":"purple"},{"cause":"Fibromyalgia in Men","htmlcolor":"purple"},{"cause":"Harmony","htmlcolor":"purple"},{"cause":"Homelessness","htmlcolor":"purple"},{"cause":"Lupus","htmlcolor":"purple"},{"cause":"Macular Degeneration","htmlcolor":"purple"},{"cause":"Mucolididoses","htmlcolor":"purple"},{"cause":"No Unattended kids in Cars","htmlcolor":"purple"},{"cause":"Pancreatic Cancer","htmlcolor":"purple"},{"cause":"Pancreatitis (Chronic)","htmlcolor":"purple"},{"cause":"Religious Tolerance","htmlcolor":"purple"},{"cause":"Rett Syndrome","htmlcolor":"purple"},{"cause":"Sarcoidosis","htmlcolor":"purple"},{"cause":"Sjorgren&#39;s Syndrome","htmlcolor":"purple"},{"cause":"Thyroid Cancer","htmlcolor":"purple"},{"cause":"Alzheimer&#39;s","htmlcolor":"purple"},{"cause":"Fibromyalgia","htmlcolor":"purple"},{"cause":"Leimyosarcoma","htmlcolor":"purple"},{"cause":"Victims of 9/11","htmlcolor":"purple"},{"cause":"Cancer (unspecified)","htmlcolor":"lavender"},{"cause":"Caregiver Appreciation","htmlcolor":"lavender"},{"cause":"Epilepsy (alt purple)","htmlcolor":"lavender"},{"cause":"Foster Care","htmlcolor":"lavender"},{"cause":"Hypokalemic Periodic Paralysis","htmlcolor":"lavender"},{"cause":"Infantile Spasms","htmlcolor":"lavender"},{"cause":"Gynecological Cancer","htmlcolor":"lavender"},{"cause":"Rett Syndrome","htmlcolor":"lavender"},{"cause":"Emphysema","htmlcolor":"orange"},{"cause":"Lung Cancer","htmlcolor":"white"},{"cause":"Lung Disease","htmlcolor":"turquoise"},{"cause":"Mesothelioma","htmlcolor":"blue"},{"cause":"Multiple Sclerosis","htmlcolor":"orange"},{"cause":"Waldenstrom's Macroglobulinemia","htmlcolor":"whitesmoke"},{"cause":"Brain Disabilities","htmlcolor":"silver"},{"cause":"Campaign for the Brain","htmlcolor":"silver"},{"cause":"Charcot-Marie-Tooth (CMT)","htmlcolor":"silver"},{"cause":"Disabled Children","htmlcolor":"silver"},{"cause":"Dyslexia","htmlcolor":"silver"},{"cause":"Elderly Abuse","htmlcolor":"silver"},{"cause":"Encephalitis","htmlcolor":"silver"},{"cause":"Niemann-Pick","htmlcolor":"silver"},{"cause":"Parkinson&#39;s Disease","htmlcolor":"silver"},{"cause":"Schizophrenia","htmlcolor":"silver"},{"cause":"Sciatic Pain","htmlcolor":"silver"},{"cause":"VACTERL","htmlcolor":"silver"},{"cause":"Brain Disorders","htmlcolor":"silver"},{"cause":"Young Onset Parkinson&#39;s Association (YOPA)","htmlcolor":"silver"},{"cause":"Alopecia","htmlcolor":"blue"},{"cause":"Ankylosing Spondylitis","htmlcolor":"blue"},{"cause":"Acute Respiratory Distress Syndrome (ARDS)","htmlcolor":"blue"},{"cause":"Anti-Bullying","htmlcolor":"blue"},{"cause":"Brachial Plexus Injuries","htmlcolor":"blue"},{"cause":"Child Abuse","htmlcolor":"blue"},{"cause":"Children&#39;s Healthy Weight","htmlcolor":"blue"},{"cause":"Colitis","htmlcolor":"blue"},{"cause":"Colon Cancer","htmlcolor":"blue"},{"cause":"Crime Victim&#39;s Rights","htmlcolor":"blue"},{"cause":"Crohn&#39;s Disease","htmlcolor":"blue"},{"cause":"Cru du Chat Syndrome","htmlcolor":"blue"},{"cause":"Drowning Awareness","htmlcolor":"blue"},{"cause":"Dysautonomia","htmlcolor":"blue"},{"cause":"Dystonia","htmlcolor":"blue"},{"cause":"Education","htmlcolor":"blue"},{"cause":"Epstein-Barr Virus","htmlcolor":"blue"},{"cause":"Erb&#39;s Palsy","htmlcolor":"blue"},{"cause":"Familial Polyposis","htmlcolor":"blue"},{"cause":"Free Speech","htmlcolor":"blue"},{"cause":"Foster Care Awareness","htmlcolor":"blue"},{"cause":"Guillain Barre Syndrome","htmlcolor":"blue"},{"cause":"Hydrocephalus (US)","htmlcolor":"blue"},{"cause":"Huntington&#39;s Disease","htmlcolor":"blue"},{"cause":"Hurricanes","htmlcolor":"blue"},{"cause":"Hystiocytosis","htmlcolor":"blue"},{"cause":"Ichthyosis","htmlcolor":"blue"},{"cause":"Interstitial Cystitis","htmlcolor":"blue"},{"cause":"Langerhans Cell Hystiocytosis","htmlcolor":"blue"},{"cause":"Leukodystrophies","htmlcolor":"blue"},{"cause":"ME/CFIDS","htmlcolor":"blue"},{"cause":"Myositis","htmlcolor":"blue"},{"cause":"Prevent School Violence","htmlcolor":"blue"},{"cause":"Osteogenesis Imperfecta (IO)","htmlcolor":"blue"},{"cause":"Pompe Disease","htmlcolor":"blue"},{"cause":"Restless Legs Syndrome","htmlcolor":"blue"},{"cause":"Steven Johnson Syndrome","htmlcolor":"blue"},{"cause":"Teens against Smoking","htmlcolor":"blue"},{"cause":"Victim&#39;s Rights","htmlcolor":"blue"},{"cause":"Victims of Hurricane Katrina","htmlcolor":"blue"},{"cause":"Save the Music","htmlcolor":"blue"},{"cause":"Water accidents","htmlcolor":"blue"},{"cause":"Water Quality and Water Safety","htmlcolor":"blue"},{"cause":"Arthritis","htmlcolor":"blue"},{"cause":"Chronic Fatigue Syndrome","htmlcolor":"blue"},{"cause":"Colorectal Cancer","htmlcolor":"blue"},{"cause":"Drunk Driving","htmlcolor":"blue"},{"cause":"Police Lost in Line of Duty","htmlcolor":"blue"},{"cause":"Transverse Myelitis","htmlcolor":"blue"},{"cause":"Alopecia","htmlcolor":"navy"},{"cause":"ARDS","htmlcolor":"navy"},{"cause":"Child Abuse","htmlcolor":"navy"},{"cause":"Chronic Fatigue Syndrome","htmlcolor":"navy"},{"cause":"Colitis","htmlcolor":"navy"},{"cause":"Colon Cancer","htmlcolor":"navy"},{"cause":"Crime Victim&#39;s Rights","htmlcolor":"navy"},{"cause":"Crohn&#39;s Disease","htmlcolor":"navy"},{"cause":"Drowning","htmlcolor":"navy"},{"cause":"Education","htmlcolor":"navy"},{"cause":"Erb&#39;s Palsy","htmlcolor":"navy"},{"cause":"Free Speech","htmlcolor":"navy"},{"cause":"Guillain Barre Syndrome","htmlcolor":"navy"},{"cause":"Hurricane Katrina","htmlcolor":"navy"},{"cause":"Death of Police Officer on Duty","htmlcolor":"navy"},{"cause":"Restless Legs Syndrome","htmlcolor":"navy"},{"cause":"Teens against smoking","htmlcolor":"navy"},{"cause":"Victim&#39;s Rights","htmlcolor":"navy"},{"cause":"Water Quality & Water Safety.","htmlcolor":"navy"},{"cause":"Arthritis","htmlcolor":"navy"},{"cause":"Colorectal Cancer","htmlcolor":"navy"},{"cause":"Epstein-Barr Virus","htmlcolor":"navy"},{"cause":"Huntington&#39;s Disease","htmlcolor":"navy"},{"cause":"Rectal Cancer","htmlcolor":"navy"},{"cause":"Water accidents","htmlcolor":"navy"},{"cause":"Addisons Disease","htmlcolor":"lightblue"},{"cause":"Chronic Illness","htmlcolor":"lightblue"},{"cause":"Cushing Syndrome","htmlcolor":"lightblue"},{"cause":"DiGeorge Sequence","htmlcolor":"lightblue"},{"cause":"Graves Disease","htmlcolor":"lightblue"},{"cause":"Hydrocephalus","htmlcolor":"lightblue"},{"cause":"Klinefelter&#39;s Syndrome","htmlcolor":"lightblue"},{"cause":"Lymphedema","htmlcolor":"lightblue"},{"cause":"Pro Choice","htmlcolor":"lightblue"},{"cause":"Prostate Cancer","htmlcolor":"lightblue"},{"cause":"Scleroderma","htmlcolor":"lightblue"},{"cause":"Shprintzen Syndrome","htmlcolor":"lightblue"},{"cause":"Thyroid Disease","htmlcolor":"lightblue"},{"cause":"Trisomy 18 and Velo-Cardio Facial Syndrome","htmlcolor":"lightblue"},{"cause":"Behcets Disease","htmlcolor":"lightblue"},{"cause":"Hyperaldosteronism","htmlcolor":"lightblue"},{"cause":"Men&#39;s Health","htmlcolor":"lightblue"},{"cause":"Spay or Neuter Pets","htmlcolor":"lightblue"},{"cause":"Adenosarcoma","htmlcolor":"yellow"},{"cause":"Amber Alert","htmlcolor":"yellow"},{"cause":"Bladder Cancer","htmlcolor":"yellow"},{"cause":"Canadian Cancer Society","htmlcolor":"yellow"},{"cause":"Carbon Monoxide Poisoning","htmlcolor":"yellow"},{"cause":"Complementary / Alternative Medicine","htmlcolor":"yellow"},{"cause":"Endometriosis","htmlcolor":"yellow"},{"cause":"Ewings Sarcoma","htmlcolor":"yellow"},{"cause":"Gulf War","htmlcolor":"yellow"},{"cause":"Hydrocephalus (Int&#39;l)","htmlcolor":"yellow"},{"cause":"Liver Cancer","htmlcolor":"yellow"},{"cause":"Liver Disease","htmlcolor":"yellow"},{"cause":"Missing Children","htmlcolor":"yellow"},{"cause":"Myxoid Liposarcoma","htmlcolor":"yellow"},{"cause":"Osteosarcoma","htmlcolor":"yellow"},{"cause":"Obesity","htmlcolor":"yellow"},{"cause":"POW/MIA","htmlcolor":"yellow"},{"cause":"Remembrance","htmlcolor":"yellow"},{"cause":"Sarcoma","htmlcolor":"yellow"},{"cause":"Spina Bifida","htmlcolor":"yellow"},{"cause":"Adoptive Parents","htmlcolor":"yellow"},{"cause":"Equality","htmlcolor":"yellow"},{"cause":"Suicide Awareness","htmlcolor":"yellow"},{"cause":"Troop or Military Support","htmlcolor":"yellow"},{"cause":"Paralysis","htmlcolor":"ivory"},{"cause":"Spinal Cord Injuries","htmlcolor":"limegreen"},{"cause":"Spinal Disorders","htmlcolor":"gray"},{"cause":"Spinal Muscular Atrophy","htmlcolor":"purple"},{"cause":"Celiac Disease, Chronic pelvic Pain","htmlcolor":"green"},{"cause":"Human Papilloma Virus","htmlcolor":"green"},{"cause":"Sexually Transmitted Diseases (STD)","htmlcolor":"green"},{"cause":"Anti-Racism","htmlcolor":"black,white"},{"cause":"Diversity","htmlcolor":"black,white"},{"cause":"Gifted Education","htmlcolor":"black,white"},{"cause":"Transitions","htmlcolor":"black,white"},{"cause":"Vaccine Awareness.","htmlcolor":"black,white"},{"cause":"Carcinoid Cancer","htmlcolor":"black,white"},{"cause":"Eczema","htmlcolor":"orchid,orange"},{"cause":"Psoriasis","htmlcolor":"orchid,orange"},{"cause":"Designated Drivers","htmlcolor":"blue,yellow"},{"cause":"Down Syndrome","htmlcolor":"blue,yellow"},{"cause":"Thoracic Outlet Syndrome","htmlcolor":"blue,yellow"},{"cause":"Pediatric Stroke","htmlcolor":"blue,purple"},{"cause":"Rheumatoid Arthritis","htmlcolor":"blue,purple"},{"cause":"Congenital Heart Defects and Disease","htmlcolor":"blue,red"},{"cause":"Hypo plastic left heart Syndrome","htmlcolor":"blue,red"},{"cause":"Olser Weber Rendu Syndrome (HHT)","htmlcolor":"blue,red"},{"cause":"Noonan&#39;s Syndrome","htmlcolor":"blue,red"},{"cause":"Pulmonary Fibrosis","htmlcolor":"blue,red"},{"cause":"Rare Lung Diseases","htmlcolor":"blue,red"},{"cause":"SADS","htmlcolor":"blue,red"},{"cause":"Aplastic Anemia","htmlcolor":"red,white"},{"cause":"Head and Neck Cancer","htmlcolor":"red,white"},{"cause":"Hereditary Hemorrhagic Telangiectasia","htmlcolor":"red,white"},{"cause":"Oral Cancer","htmlcolor":"red,white"},{"cause":"DVT","htmlcolor":"red,white"},{"cause":"Squamous Cell Carcinoma","htmlcolor":"red,white"},{"cause":"Domestic Violence","htmlcolor":"teal,purple"},{"cause":"Sexual Assault","htmlcolor":"teal,purple"},{"cause":"Autoimmune Hepatitis","htmlcolor":"purple,yellow"},{"cause":"Chemical Injury","htmlcolor":"purple,yellow"},{"cause":"the relationship between Lupus and Endometriosis","htmlcolor":"purple,yellow"},{"cause":"Hepatitis C","htmlcolor":"red,yellow"},{"cause":"HIV/HCV Co-Infection","htmlcolor":"red,yellow"},{"cause":"Surviving family members of Suicide victims","htmlcolor":"red,yellow"},{"cause":"Cervical Cancer","htmlcolor":"teal,white"},{"cause":"Mourning a Sister","htmlcolor":"black"},{"cause":"Mourning a Daughter","htmlcolor":"black"},{"cause":"Loss of a female child","htmlcolor":"black"},{"cause":"Loss of a Brother","htmlcolor":"black,blue"},{"cause":"mourning a brother","htmlcolor":"black,blue"},{"cause":"mourning a son.","htmlcolor":"black,blue"},{"cause":"Loss of a male child","htmlcolor":"black,blue"},{"cause":"Acid Reflux","htmlcolor":"purple"},{"cause":"Bulimia Nervosa","htmlcolor":"purple"},{"cause":"Eating Disorders","htmlcolor":"purple"},{"cause":"Eosinophilic Disorders","htmlcolor":"purple"},{"cause":"Gastric Cancer","htmlcolor":"purple"},{"cause":"Gastroesophageal Reflux Disease(GERD)","htmlcolor":"purple"},{"cause":"Pulmonary Hypertension","htmlcolor":"purple"},{"cause":"Small Intestine Cancer","htmlcolor":"purple"},{"cause":"Anorexia Nervosa","htmlcolor":"purple"},{"cause":"Esophageal Cancer","htmlcolor":"purple"},{"cause":"Irritable Bowel Syndrome(IBS)","htmlcolor":"purple"},{"cause":"Stomach Cancer","htmlcolor":"purple"},{"cause":"Thyroid Cancer","htmlcolor":"pink,purple,teal"},{"cause":"Murder Victims","htmlcolor":"black,red"},{"cause":"Loss of a Fire fighter on Duty","htmlcolor":"black,red"},{"cause":"Murdered Children","htmlcolor":"black,red"}]
